{
  "mcpServers": {
    "agent-mcp": {
      "type": "stdio",
      "command": "node",
      "args": ["dist/packages/ai/agent-mcp/src/index.js"],
      "env": {
        "DATABASE_PATH": "tmp/agent-mcp/agents-dev.db",
        "LMSTUDIO_BASE_URL": "http://localhost:1234/v1"
      }
    },
    "agent-mcp-published": {
      "type": "stdio",
      "command": "npx",
      "args": ["-y", "@adhd/agent-mcp@latest"],
      "env": {
        "DATABASE_PATH": "tmp/agent-mcp/agents-published.db",
        "LMSTUDIO_BASE_URL": "http://localhost:1234/v1"
      }
    }
  }
}
