{
  "schema_version": 3,
  "title": "task-schema-foundation",
  "dag": "dag.json",
  "current_state": "audit-final",
  "states": {
    "schema-columns": {
      "status": "complete",
      "executor": null,
      "started_at": "2026-06-14T03:38:47.767Z",
      "done_at": "2026-06-14T03:39:54.368Z",
      "start_ref": "fd9c609fcfd514216a546bd0948bc9282729841e",
      "end_ref": "8a848ce673c0596894f22c3891dd557b2d16f916"
    },
    "task-types": {
      "status": "complete",
      "executor": null,
      "started_at": "2026-06-14T03:40:31.166Z",
      "done_at": "2026-06-14T03:42:57.497Z",
      "start_ref": "43013ceff6f4e0f03b85a62e76772df160506c8b",
      "end_ref": "96f13ec91d9d5d35ad4d070024c5f79fef4678ea"
    },
    "audit-foundation": {
      "status": "complete",
      "executor": null,
      "started_at": "2026-06-14T03:43:06.085Z",
      "done_at": "2026-06-14T03:43:14.594Z",
      "start_ref": "da52da3337e47002477469f1237fda3da8cb9bf3",
      "end_ref": "1e0dff2b5d72a6de5ceeb967323ec298abe552fe"
    },
    "code-review": {
      "status": "complete",
      "executor": null,
      "started_at": "2026-06-15T15:08:49.555Z",
      "done_at": "2026-06-15T15:08:49.900Z",
      "start_ref": "7b7066a77ce086712033ad0afa520b7cb921565f",
      "end_ref": "23ff14b01072b82318512acb3098594476229b6f"
    },
    "audit-final": {
      "status": "pending",
      "executor": null,
      "started_at": null,
      "done_at": null,
      "start_ref": null,
      "end_ref": null
    },
    "docs-and-publish": {
      "status": "pending",
      "executor": null,
      "started_at": null,
      "done_at": null,
      "start_ref": null,
      "end_ref": null
    }
  },
  "transition_log": [
    {
      "ts": "2026-06-14T03:39:46.454Z",
      "from": "schema-columns",
      "to": "schema-columns",
      "start_ref": "fd9c609fcfd514216a546bd0948bc9282729841e",
      "end_ref": "b3ce2614734b6c6aef3a84f3d0e2544fdf6f3ae2",
      "audit_exit": 1,
      "audit_criteria_passed": 0,
      "audit_criteria_total": 0,
      "by": "pseudosky",
      "note": "4 cols + 2 statuses, single migration 0004"
    },
    {
      "ts": "2026-06-14T03:39:54.368Z",
      "from": "task-types",
      "to": "schema-columns",
      "start_ref": "fd9c609fcfd514216a546bd0948bc9282729841e",
      "end_ref": "8a848ce673c0596894f22c3891dd557b2d16f916",
      "audit_exit": 1,
      "audit_criteria_passed": 0,
      "audit_criteria_total": 0,
      "by": "pseudosky",
      "note": "4 cols + 2 statuses, single migration 0004"
    },
    {
      "ts": "2026-06-14T03:42:57.497Z",
      "from": "task-types",
      "to": "task-types",
      "start_ref": "43013ceff6f4e0f03b85a62e76772df160506c8b",
      "end_ref": "96f13ec91d9d5d35ad4d070024c5f79fef4678ea",
      "audit_exit": 0,
      "audit_criteria_passed": 0,
      "audit_criteria_total": 0,
      "by": "pseudosky",
      "note": "types→validation→store; build green, 52/52 tests pass"
    },
    {
      "ts": "2026-06-14T03:43:14.594Z",
      "from": "audit-foundation",
      "to": "audit-foundation",
      "start_ref": "da52da3337e47002477469f1237fda3da8cb9bf3",
      "end_ref": "1e0dff2b5d72a6de5ceeb967323ec298abe552fe",
      "audit_exit": 0,
      "audit_criteria_passed": 0,
      "audit_criteria_total": 0,
      "by": "pseudosky",
      "note": "foundation audit green"
    },
    {
      "ts": "2026-06-15T15:08:49.900Z",
      "from": "code-review",
      "to": "code-review",
      "start_ref": "7b7066a77ce086712033ad0afa520b7cb921565f",
      "end_ref": "23ff14b01072b82318512acb3098594476229b6f",
      "audit_exit": 2,
      "audit_criteria_passed": 0,
      "audit_criteria_total": 0,
      "by": "pseudosky",
      "note": "Human sign-off recorded (pseudosky, 2026-06-15): features verified end-to-end live — real-DB FK migration preserved task_events; recursive DAG with all tool calls confirmed via calc-server.log + task_events + usage_query."
    }
  ],
  "amendment_log": [],
  "authored_with": {
    "plugin": "workflow",
    "version": "0.8.8",
    "hash": "fd74ba3328ea"
  }
}
